{
  "meta": {
    "title": "Wortzerlegung — Morphologische Analyse",
    "description": "Quranische Wörter in Präfixe, Wurzel, Muster und Suffixe zerlegen. Trainiert morphologisches Erkennen.",
    "totalExercises": 117,
    "sources": [
      {
        "title": "Wright's Arabic Grammar, Vol. I (Morphology)",
        "url": "https://archive.org/details/WrightsArabicGrammar1Of2"
      },
      {
        "title": "Quranic Arabic Corpus",
        "url": "https://corpus.quran.com/"
      },
      {
        "title": "Lane's Lexicon",
        "url": "https://ejtaal.net/aa/"
      }
    ]
  },
  "exercises": [
    {
      "id": "dec_001",
      "word": "كَتَبَ",
      "root": "ك-ت-ب",
      "prefixes": "—",
      "pattern": "فَعَلَ (I)",
      "suffixes": "—",
      "meaning": "er schrieb",
      "ref": "2:187",
      "verifyUrl": "https://corpus.quran.com/wordbyword.jsp?chapter=2&verse=187"
    },
    {
      "id": "dec_002",
      "word": "يَعْلَمُونَ",
      "root": "ع-ل-م",
      "prefixes": "يَـ",
      "pattern": "يَفْعَلُ (I)",
      "suffixes": "ونَ",
      "meaning": "sie wissen",
      "ref": "2:13",
      "verifyUrl": "https://corpus.quran.com/wordbyword.jsp?chapter=2&verse=13"
    },
    {
      "id": "dec_003",
      "word": "خَلَقَ",
      "root": "خ-ل-ق",
      "prefixes": "—",
      "pattern": "فَعَلَ (I)",
      "suffixes": "—",
      "meaning": "er erschuf",
      "ref": "96:1",
      "verifyUrl": "https://corpus.quran.com/wordbyword.jsp?chapter=96&verse=1"
    },
    {
      "id": "dec_004",
      "word": "ضَرَبَ",
      "root": "ض-ر-ب",
      "prefixes": "—",
      "pattern": "فَعَلَ (I)",
      "suffixes": "—",
      "meaning": "er schlug/prägte",
      "ref": "2:26",
      "verifyUrl": "https://corpus.quran.com/wordbyword.jsp?chapter=2&verse=26"
    },
    {
      "id": "dec_005",
      "word": "جَعَلَ",
      "root": "ج-ع-ل",
      "prefixes": "—",
      "pattern": "فَعَلَ (I)",
      "suffixes": "—",
      "meaning": "er machte/setzte",
      "ref": "2:22",
      "verifyUrl": "https://corpus.quran.com/wordbyword.jsp?chapter=2&verse=22"
    },
    {
      "id": "dec_006",
      "word": "عَلِمَ",
      "root": "ع-ل-م",
      "prefixes": "—",
      "pattern": "فَعِلَ (I)",
      "suffixes": "—",
      "meaning": "er wusste",
      "ref": "2:33",
      "verifyUrl": "https://corpus.quran.com/wordbyword.jsp?chapter=2&verse=33"
    },
    {
      "id": "dec_007",
      "word": "حَسِبَ",
      "root": "ح-س-ب",
      "prefixes": "—",
      "pattern": "فَعِلَ (I)",
      "suffixes": "—",
      "meaning": "er meinte/dachte",
      "ref": "2:214",
      "verifyUrl": "https://corpus.quran.com/wordbyword.jsp?chapter=2&verse=214"
    },
    {
      "id": "dec_008",
      "word": "كَبُرَ",
      "root": "ك-ب-ر",
      "prefixes": "—",
      "pattern": "فَعُلَ (I)",
      "suffixes": "—",
      "meaning": "es war groß",
      "ref": "2:45",
      "verifyUrl": "https://corpus.quran.com/wordbyword.jsp?chapter=2&verse=45"
    },
    {
      "id": "dec_009",
      "word": "تَقُولُونَ",
      "root": "ق-و-ل",
      "prefixes": "تَـ",
      "pattern": "تَفْعُلُ (I)",
      "suffixes": "ونَ",
      "meaning": "ihr sagt",
      "ref": "2:80",
      "verifyUrl": "https://corpus.quran.com/wordbyword.jsp?chapter=2&verse=80"
    },
    {
      "id": "dec_010",
      "word": "نَسْتَعِينُ",
      "root": "ع-و-ن",
      "prefixes": "نَـ + سْتَـ",
      "pattern": "نَسْتَفْعِلُ (X)",
      "suffixes": "—",
      "meaning": "wir bitten um Hilfe",
      "ref": "1:5",
      "note": "Hohlverb (Wurzel mit medialem Waw). Im Imperfekt Form X fällt der mittlere schwache Radikal aus und wird als Langvokal kompensiert: يَسْتَعْوِنُ → يَسْتَعِينُ. Die Wurzel ist ع-و-ن, nicht ع-ي-ن (Auge).",
      "verifyUrl": "https://corpus.quran.com/wordbyword.jsp?chapter=1&verse=5"
    },
    {
      "id": "dec_011",
      "word": "عَلَّمَ",
      "root": "ع-ل-م",
      "prefixes": "—",
      "pattern": "فَعَّلَ (II)",
      "suffixes": "—",
      "meaning": "er lehrte",
      "ref": "96:4",
      "verifyUrl": "https://corpus.quran.com/wordbyword.jsp?chapter=96&verse=4"
    },
    {
      "id": "dec_012",
      "word": "نَزَّلَ",
      "root": "ن-ز-ل",
      "prefixes": "—",
      "pattern": "فَعَّلَ (II)",
      "suffixes": "—",
      "meaning": "er sandte herab (stückweise)",
      "ref": "3:3",
      "verifyUrl": "https://corpus.quran.com/wordbyword.jsp?chapter=3&verse=3"
    },
    {
      "id": "dec_013",
      "word": "كَذَّبَ",
      "root": "ك-ذ-ب",
      "prefixes": "—",
      "pattern": "فَعَّلَ (II)",
      "suffixes": "—",
      "meaning": "er bezichtigte der Lüge",
      "ref": "3:11",
      "verifyUrl": "https://corpus.quran.com/wordbyword.jsp?chapter=3&verse=11"
    },
    {
      "id": "dec_014",
      "word": "يُصَلُّونَ",
      "root": "ص-ل-و",
      "prefixes": "يُـ",
      "pattern": "يُفَعِّلُ (II)",
      "suffixes": "ونَ",
      "meaning": "sie wenden sich zu (konventionell: sie segnen)",
      "ref": "33:56",
      "verifyUrl": "https://corpus.quran.com/wordbyword.jsp?chapter=33&verse=56"
    },
    {
      "id": "dec_015",
      "word": "بَشَّرَ",
      "root": "ب-ش-ر",
      "prefixes": "—",
      "pattern": "فَعَّلَ (II)",
      "suffixes": "—",
      "meaning": "er verkündete frohe Botschaft",
      "ref": "2:25",
      "verifyUrl": "https://corpus.quran.com/wordbyword.jsp?chapter=2&verse=25"
    },
    {
      "id": "dec_016",
      "word": "قَاتَلَ",
      "root": "ق-ت-ل",
      "prefixes": "—",
      "pattern": "فَاعَلَ (III)",
      "suffixes": "—",
      "meaning": "er kämpfte (gegen)",
      "ref": "2:190",
      "verifyUrl": "https://corpus.quran.com/wordbyword.jsp?chapter=2&verse=190"
    },
    {
      "id": "dec_017",
      "word": "نَادَى",
      "root": "ن-د-و",
      "prefixes": "—",
      "pattern": "فَاعَلَ (III)",
      "suffixes": "—",
      "meaning": "er rief",
      "ref": "3:39",
      "verifyUrl": "https://corpus.quran.com/wordbyword.jsp?chapter=3&verse=39"
    },
    {
      "id": "dec_018",
      "word": "يُجَاهِدُونَ",
      "root": "ج-ه-د",
      "prefixes": "يُـ",
      "pattern": "يُفَاعِلُ (III)",
      "suffixes": "ونَ",
      "meaning": "sie streben/kämpfen",
      "ref": "9:20",
      "verifyUrl": "https://corpus.quran.com/wordbyword.jsp?chapter=9&verse=20"
    },
    {
      "id": "dec_019",
      "word": "يُنَافِقُونَ",
      "root": "ن-ف-ق",
      "prefixes": "يُـ",
      "pattern": "يُفَاعِلُ (III)",
      "suffixes": "ونَ",
      "meaning": "sie heucheln",
      "ref": "2:14",
      "verifyUrl": "https://corpus.quran.com/wordbyword.jsp?chapter=2&verse=14"
    },
    {
      "id": "dec_020",
      "word": "حَاسَبَ",
      "root": "ح-س-ب",
      "prefixes": "—",
      "pattern": "فَاعَلَ (III)",
      "suffixes": "—",
      "meaning": "er rechnete ab mit",
      "ref": "65:8",
      "verifyUrl": "https://corpus.quran.com/wordbyword.jsp?chapter=65&verse=8"
    },
    {
      "id": "dec_021",
      "word": "أَنْزَلَ",
      "root": "ن-ز-ل",
      "prefixes": "أَ",
      "pattern": "أَفْعَلَ (IV)",
      "suffixes": "—",
      "meaning": "er sandte herab (auf einmal)",
      "ref": "2:4",
      "verifyUrl": "https://corpus.quran.com/wordbyword.jsp?chapter=2&verse=4"
    },
    {
      "id": "dec_022",
      "word": "أَسْلَمَ",
      "root": "س-ل-م",
      "prefixes": "أَ",
      "pattern": "أَفْعَلَ (IV)",
      "suffixes": "—",
      "meaning": "er übergab sich",
      "ref": "2:112",
      "verifyUrl": "https://corpus.quran.com/wordbyword.jsp?chapter=2&verse=112"
    },
    {
      "id": "dec_023",
      "word": "يُؤْمِنُونَ",
      "root": "أ-م-ن",
      "prefixes": "يُـ",
      "pattern": "يُفْعِلُ (IV)",
      "suffixes": "ونَ",
      "meaning": "sie glauben",
      "ref": "2:3",
      "verifyUrl": "https://corpus.quran.com/wordbyword.jsp?chapter=2&verse=3"
    },
    {
      "id": "dec_024",
      "word": "أَحْسَنَ",
      "root": "ح-س-ن",
      "prefixes": "أَ",
      "pattern": "أَفْعَلَ (IV)",
      "suffixes": "—",
      "meaning": "er tat Gutes",
      "ref": "12:23",
      "verifyUrl": "https://corpus.quran.com/wordbyword.jsp?chapter=12&verse=23"
    },
    {
      "id": "dec_025",
      "word": "يُنْفِقُونَ",
      "root": "ن-ف-ق",
      "prefixes": "يُـ",
      "pattern": "يُفْعِلُ (IV)",
      "suffixes": "ونَ",
      "meaning": "sie spenden",
      "ref": "2:3",
      "verifyUrl": "https://corpus.quran.com/wordbyword.jsp?chapter=2&verse=3"
    },
    {
      "id": "dec_026",
      "word": "تَعَلَّمَ",
      "root": "ع-ل-م",
      "prefixes": "تَـ",
      "pattern": "تَفَعَّلَ (V)",
      "suffixes": "—",
      "meaning": "er lernte (selbst)",
      "ref": "2:102",
      "verifyUrl": "https://corpus.quran.com/wordbyword.jsp?chapter=2&verse=102"
    },
    {
      "id": "dec_027",
      "word": "تَوَفَّى",
      "root": "و-ف-ي",
      "prefixes": "تَـ",
      "pattern": "تَفَعَّلَ (V)",
      "suffixes": "—",
      "meaning": "er nahm vollständig",
      "ref": "3:55",
      "verifyUrl": "https://corpus.quran.com/wordbyword.jsp?chapter=3&verse=55"
    },
    {
      "id": "dec_028",
      "word": "يَتَذَكَّرُونَ",
      "root": "ذ-ك-ر",
      "prefixes": "يَـ + تَـ",
      "pattern": "يَتَفَعَّلُ (V)",
      "suffixes": "ونَ",
      "meaning": "sie bedenken",
      "ref": "2:269",
      "verifyUrl": "https://corpus.quran.com/wordbyword.jsp?chapter=2&verse=269"
    },
    {
      "id": "dec_029",
      "word": "تَوَكَّلَ",
      "root": "و-ك-ل",
      "prefixes": "تَـ",
      "pattern": "تَفَعَّلَ (V)",
      "suffixes": "—",
      "meaning": "er vertraute (auf)",
      "ref": "3:122",
      "verifyUrl": "https://corpus.quran.com/wordbyword.jsp?chapter=3&verse=122"
    },
    {
      "id": "dec_030",
      "word": "يَتَفَكَّرُونَ",
      "root": "ف-ك-ر",
      "prefixes": "يَـ + تَـ",
      "pattern": "يَتَفَعَّلُ (V)",
      "suffixes": "ونَ",
      "meaning": "sie denken nach",
      "ref": "3:191",
      "verifyUrl": "https://corpus.quran.com/wordbyword.jsp?chapter=3&verse=191"
    },
    {
      "id": "dec_031",
      "word": "تَعَاوَنُوا",
      "root": "ع-و-ن",
      "prefixes": "تَـ",
      "pattern": "تَفَاعَلَ (VI)",
      "suffixes": "وا",
      "meaning": "helft einander",
      "ref": "5:2",
      "verifyUrl": "https://corpus.quran.com/wordbyword.jsp?chapter=5&verse=2"
    },
    {
      "id": "dec_032",
      "word": "يَتَسَاءَلُونَ",
      "root": "س-أ-ل",
      "prefixes": "يَـ + تَـ",
      "pattern": "يَتَفَاعَلُ (VI)",
      "suffixes": "ونَ",
      "meaning": "sie fragen einander",
      "ref": "78:1",
      "verifyUrl": "https://corpus.quran.com/wordbyword.jsp?chapter=78&verse=1"
    },
    {
      "id": "dec_033",
      "word": "تَبَارَكَ",
      "root": "ب-ر-ك",
      "prefixes": "تَـ",
      "pattern": "تَفَاعَلَ (VI)",
      "suffixes": "—",
      "meaning": "gesegnet ist",
      "ref": "25:1",
      "verifyUrl": "https://corpus.quran.com/wordbyword.jsp?chapter=25&verse=1"
    },
    {
      "id": "dec_034",
      "word": "تَنَازَعَ",
      "root": "ن-ز-ع",
      "prefixes": "تَـ",
      "pattern": "تَفَاعَلَ (VI)",
      "suffixes": "—",
      "meaning": "sie stritten (miteinander)",
      "ref": "8:46",
      "verifyUrl": "https://corpus.quran.com/wordbyword.jsp?chapter=8&verse=46"
    },
    {
      "id": "dec_035",
      "word": "تَوَاصَوْا",
      "root": "و-ص-ي",
      "prefixes": "تَـ",
      "pattern": "تَفَاعَلَ (VI)",
      "suffixes": "وْا",
      "meaning": "sie empfahlen einander",
      "ref": "103:3",
      "verifyUrl": "https://corpus.quran.com/wordbyword.jsp?chapter=103&verse=3"
    },
    {
      "id": "dec_036",
      "word": "اِنْفَطَرَتْ",
      "root": "ف-ط-ر",
      "prefixes": "اِنْـ",
      "pattern": "اِنْفَعَلَ (VII)",
      "suffixes": "تْ",
      "meaning": "sie spaltete sich",
      "ref": "82:1",
      "verifyUrl": "https://corpus.quran.com/wordbyword.jsp?chapter=82&verse=1"
    },
    {
      "id": "dec_037",
      "word": "اِنْشَقَّ",
      "root": "ش-ق-ق",
      "prefixes": "اِنْـ",
      "pattern": "اِنْفَعَلَ (VII)",
      "suffixes": "—",
      "meaning": "er spaltete sich",
      "ref": "54:1",
      "verifyUrl": "https://corpus.quran.com/wordbyword.jsp?chapter=54&verse=1"
    },
    {
      "id": "dec_038",
      "word": "يَنْقَلِبُ",
      "root": "ق-ل-ب",
      "prefixes": "يَـ + نْـ",
      "pattern": "يَنْفَعِلُ (VII)",
      "suffixes": "—",
      "meaning": "er kehrt um",
      "ref": "26:227",
      "verifyUrl": "https://corpus.quran.com/wordbyword.jsp?chapter=26&verse=227"
    },
    {
      "id": "dec_039",
      "word": "اِهْتَدَى",
      "root": "ه-د-ي",
      "prefixes": "اِـ + ـتَـ",
      "pattern": "اِفْتَعَلَ (VIII)",
      "suffixes": "—",
      "meaning": "er fand den Weg",
      "ref": "2:16",
      "verifyUrl": "https://corpus.quran.com/wordbyword.jsp?chapter=2&verse=16"
    },
    {
      "id": "dec_040",
      "word": "اِتَّقَى",
      "root": "و-ق-ي",
      "prefixes": "اِتَّـ",
      "pattern": "اِفْتَعَلَ (VIII)",
      "suffixes": "—",
      "meaning": "er schützte sich / er war auf der Hut",
      "ref": "2:189",
      "verifyUrl": "https://corpus.quran.com/wordbyword.jsp?chapter=2&verse=189"
    },
    {
      "id": "dec_041",
      "word": "يَكْتَسِبُونَ",
      "root": "ك-س-ب",
      "prefixes": "يَـ + ـتَـ",
      "pattern": "يَفْتَعِلُ (VIII)",
      "suffixes": "ونَ",
      "meaning": "sie erwerben",
      "ref": "2:79",
      "verifyUrl": "https://corpus.quran.com/wordbyword.jsp?chapter=2&verse=79"
    },
    {
      "id": "dec_042",
      "word": "اِخْتَلَفَ",
      "root": "خ-ل-ف",
      "prefixes": "اِـ + ـتَـ",
      "pattern": "اِفْتَعَلَ (VIII)",
      "suffixes": "—",
      "meaning": "er war uneins",
      "ref": "2:213",
      "verifyUrl": "https://corpus.quran.com/wordbyword.jsp?chapter=2&verse=213"
    },
    {
      "id": "dec_043",
      "word": "اِجْتَبَى",
      "root": "ج-ب-ي",
      "prefixes": "اِـ + ـتَـ",
      "pattern": "اِفْتَعَلَ (VIII)",
      "suffixes": "—",
      "meaning": "er erwählte",
      "ref": "16:121",
      "verifyUrl": "https://corpus.quran.com/wordbyword.jsp?chapter=16&verse=121"
    },
    {
      "id": "dec_044",
      "word": "اِحْمَرَّ",
      "root": "ح-م-ر",
      "prefixes": "اِـ",
      "pattern": "اِفْعَلَّ (IX)",
      "suffixes": "—",
      "meaning": "er wurde rot",
      "ref": "—",
      "verifyUrl": "https://corpus.quran.com/qurandictionary.jsp?q=Hmr"
    },
    {
      "id": "dec_045",
      "word": "اِسْوَدَّتْ",
      "root": "س-و-د",
      "prefixes": "اِـ",
      "pattern": "اِفْعَلَّ (IX)",
      "suffixes": "تْ",
      "meaning": "sie wurde schwarz",
      "ref": "3:106",
      "verifyUrl": "https://corpus.quran.com/wordbyword.jsp?chapter=3&verse=106"
    },
    {
      "id": "dec_046",
      "word": "اِسْتَغْفَرَ",
      "root": "غ-ف-ر",
      "prefixes": "اِسْتَـ",
      "pattern": "اِسْتَفْعَلَ (X)",
      "suffixes": "—",
      "meaning": "er bat um Vergebung",
      "ref": "47:19",
      "verifyUrl": "https://corpus.quran.com/wordbyword.jsp?chapter=47&verse=19"
    },
    {
      "id": "dec_047",
      "word": "يَسْتَطِيعُونَ",
      "root": "ط-و-ع",
      "prefixes": "يَـ + سْتَـ",
      "pattern": "يَسْتَفْعِلُ (X)",
      "suffixes": "ونَ",
      "meaning": "sie können/vermögen",
      "ref": "2:217",
      "verifyUrl": "https://corpus.quran.com/wordbyword.jsp?chapter=2&verse=217"
    },
    {
      "id": "dec_048",
      "word": "اِسْتَقَامَ",
      "root": "ق-و-م",
      "prefixes": "اِسْتَـ",
      "pattern": "اِسْتَفْعَلَ (X)",
      "suffixes": "—",
      "meaning": "er war aufrichtig/gerade",
      "ref": "41:6",
      "verifyUrl": "https://corpus.quran.com/wordbyword.jsp?chapter=41&verse=6"
    },
    {
      "id": "dec_049",
      "word": "يَسْتَكْبِرُونَ",
      "root": "ك-ب-ر",
      "prefixes": "يَـ + سْتَـ",
      "pattern": "يَسْتَفْعِلُ (X)",
      "suffixes": "ونَ",
      "meaning": "sie sind hochmütig",
      "ref": "7:36",
      "verifyUrl": "https://corpus.quran.com/wordbyword.jsp?chapter=7&verse=36"
    },
    {
      "id": "dec_050",
      "word": "اِسْتَجَابَ",
      "root": "ج-و-ب",
      "prefixes": "اِسْتَـ",
      "pattern": "اِسْتَفْعَلَ (X)",
      "suffixes": "—",
      "meaning": "er antwortete/erhörte",
      "ref": "2:186",
      "verifyUrl": "https://corpus.quran.com/wordbyword.jsp?chapter=2&verse=186"
    },
    {
      "id": "dec_051",
      "word": "كَاتِبٌ",
      "root": "ك-ت-ب",
      "prefixes": "—",
      "pattern": "فَاعِل (AP I)",
      "suffixes": "—",
      "meaning": "Schreibender",
      "ref": "2:282",
      "verifyUrl": "https://corpus.quran.com/wordbyword.jsp?chapter=2&verse=282"
    },
    {
      "id": "dec_052",
      "word": "عَالِمٌ",
      "root": "ع-ل-م",
      "prefixes": "—",
      "pattern": "فَاعِل (AP I)",
      "suffixes": "—",
      "meaning": "Wissender",
      "ref": "6:73",
      "verifyUrl": "https://corpus.quran.com/wordbyword.jsp?chapter=6&verse=73"
    },
    {
      "id": "dec_053",
      "word": "صَابِرِينَ",
      "root": "ص-ب-ر",
      "prefixes": "—",
      "pattern": "فَاعِل (AP I)",
      "suffixes": "ينَ",
      "meaning": "Geduldige",
      "ref": "2:153",
      "verifyUrl": "https://corpus.quran.com/wordbyword.jsp?chapter=2&verse=153"
    },
    {
      "id": "dec_054",
      "word": "كَافِرُونَ",
      "root": "ك-ف-ر",
      "prefixes": "—",
      "pattern": "فَاعِل (AP I)",
      "suffixes": "ونَ",
      "meaning": "Verdeckende/Leugnende",
      "ref": "109:1",
      "verifyUrl": "https://corpus.quran.com/wordbyword.jsp?chapter=109&verse=1"
    },
    {
      "id": "dec_055",
      "word": "ظَالِمِينَ",
      "root": "ظ-ل-م",
      "prefixes": "—",
      "pattern": "فَاعِل (AP I)",
      "suffixes": "ينَ",
      "meaning": "Ungerechte",
      "ref": "2:35",
      "verifyUrl": "https://corpus.quran.com/wordbyword.jsp?chapter=2&verse=35"
    },
    {
      "id": "dec_056",
      "word": "مُسْلِمُونَ",
      "root": "س-ل-م",
      "prefixes": "مُـ",
      "pattern": "مُفْعِل (AP IV)",
      "suffixes": "ونَ",
      "meaning": "Ergebene",
      "ref": "2:132",
      "verifyUrl": "https://corpus.quran.com/wordbyword.jsp?chapter=2&verse=132"
    },
    {
      "id": "dec_057",
      "word": "مُؤْمِنِينَ",
      "root": "أ-م-ن",
      "prefixes": "مُـ",
      "pattern": "مُفْعِل (AP IV)",
      "suffixes": "ينَ",
      "meaning": "Glaubende",
      "ref": "2:223",
      "verifyUrl": "https://corpus.quran.com/wordbyword.jsp?chapter=2&verse=223"
    },
    {
      "id": "dec_058",
      "word": "مُنَافِقِينَ",
      "root": "ن-ف-ق",
      "prefixes": "مُـ",
      "pattern": "مُفَاعِل (AP III)",
      "suffixes": "ينَ",
      "meaning": "Heuchler",
      "ref": "4:138",
      "verifyUrl": "https://corpus.quran.com/wordbyword.jsp?chapter=4&verse=138"
    },
    {
      "id": "dec_059",
      "word": "مُتَّقِينَ",
      "root": "و-ق-ي",
      "prefixes": "مُـ + ـتَّـ",
      "pattern": "مُفْتَعِل (AP VIII)",
      "suffixes": "ينَ",
      "meaning": "die sich Hütenden / die auf der Hut Seienden",
      "ref": "2:2",
      "verifyUrl": "https://corpus.quran.com/wordbyword.jsp?chapter=2&verse=2"
    },
    {
      "id": "dec_060",
      "word": "مُسْتَقِيمَ",
      "root": "ق-و-م",
      "prefixes": "مُـ + سْتَـ",
      "pattern": "مُسْتَفْعِل (AP X)",
      "suffixes": "—",
      "meaning": "gerade/aufrecht",
      "ref": "1:6",
      "verifyUrl": "https://corpus.quran.com/wordbyword.jsp?chapter=1&verse=6"
    },
    {
      "id": "dec_061",
      "word": "مَكْتُوبٌ",
      "root": "ك-ت-ب",
      "prefixes": "مَـ",
      "pattern": "مَفْعُول (PP I)",
      "suffixes": "—",
      "meaning": "Geschriebenes",
      "ref": "7:157",
      "verifyUrl": "https://corpus.quran.com/wordbyword.jsp?chapter=7&verse=157"
    },
    {
      "id": "dec_062",
      "word": "مَعْرُوفٌ",
      "root": "ع-ر-ف",
      "prefixes": "مَـ",
      "pattern": "مَفْعُول (PP I)",
      "suffixes": "—",
      "meaning": "Anerkanntes/Gutes",
      "ref": "2:178",
      "verifyUrl": "https://corpus.quran.com/wordbyword.jsp?chapter=2&verse=178"
    },
    {
      "id": "dec_063",
      "word": "مَعْلُومٌ",
      "root": "ع-ل-م",
      "prefixes": "مَـ",
      "pattern": "مَفْعُول (PP I)",
      "suffixes": "—",
      "meaning": "Bekanntes",
      "ref": "15:4",
      "verifyUrl": "https://corpus.quran.com/wordbyword.jsp?chapter=15&verse=4"
    },
    {
      "id": "dec_064",
      "word": "مُنْزَلٌ",
      "root": "ن-ز-ل",
      "prefixes": "مُـ",
      "pattern": "مُفْعَل (PP IV)",
      "suffixes": "—",
      "meaning": "Herabgesandtes",
      "ref": "6:114",
      "verifyUrl": "https://corpus.quran.com/wordbyword.jsp?chapter=6&verse=114"
    },
    {
      "id": "dec_065",
      "word": "مُحَمَّدٌ",
      "root": "ح-م-د",
      "prefixes": "مُـ",
      "pattern": "مُفَعَّل (PP II)",
      "suffixes": "—",
      "meaning": "der Gelobte",
      "ref": "3:144",
      "verifyUrl": "https://corpus.quran.com/wordbyword.jsp?chapter=3&verse=144"
    },
    {
      "id": "dec_066",
      "word": "كِتَابٌ",
      "root": "ك-ت-ب",
      "prefixes": "—",
      "pattern": "فِعَال",
      "suffixes": "—",
      "meaning": "Buch/Schrift",
      "ref": "2:2",
      "verifyUrl": "https://corpus.quran.com/wordbyword.jsp?chapter=2&verse=2"
    },
    {
      "id": "dec_067",
      "word": "عَذَابٌ",
      "root": "ع-ذ-ب",
      "prefixes": "—",
      "pattern": "فَعَال",
      "suffixes": "—",
      "meaning": "Strafe",
      "ref": "2:7",
      "verifyUrl": "https://corpus.quran.com/wordbyword.jsp?chapter=2&verse=7"
    },
    {
      "id": "dec_068",
      "word": "عِلْمٌ",
      "root": "ع-ل-م",
      "prefixes": "—",
      "pattern": "فِعْل",
      "suffixes": "—",
      "meaning": "Wissen",
      "ref": "2:120",
      "verifyUrl": "https://corpus.quran.com/wordbyword.jsp?chapter=2&verse=120"
    },
    {
      "id": "dec_069",
      "word": "حُكْمٌ",
      "root": "ح-ك-م",
      "prefixes": "—",
      "pattern": "فُعْل",
      "suffixes": "—",
      "meaning": "Urteil/Herrschaft",
      "ref": "12:40",
      "verifyUrl": "https://corpus.quran.com/wordbyword.jsp?chapter=12&verse=40"
    },
    {
      "id": "dec_070",
      "word": "رَسُولٌ",
      "root": "ر-س-ل",
      "prefixes": "—",
      "pattern": "فَعُول",
      "suffixes": "—",
      "meaning": "Gesandter",
      "ref": "2:87",
      "verifyUrl": "https://corpus.quran.com/wordbyword.jsp?chapter=2&verse=87"
    },
    {
      "id": "dec_071",
      "word": "صِرَاطٌ",
      "root": "ص-ر-ط",
      "prefixes": "—",
      "pattern": "فِعَال",
      "suffixes": "—",
      "meaning": "Weg/Straße",
      "ref": "1:6",
      "verifyUrl": "https://corpus.quran.com/wordbyword.jsp?chapter=1&verse=6"
    },
    {
      "id": "dec_072",
      "word": "قَوْلٌ",
      "root": "ق-و-ل",
      "prefixes": "—",
      "pattern": "فَعْل",
      "suffixes": "—",
      "meaning": "Wort/Rede",
      "ref": "2:235",
      "verifyUrl": "https://corpus.quran.com/wordbyword.jsp?chapter=2&verse=235"
    },
    {
      "id": "dec_073",
      "word": "حَقٌّ",
      "root": "ح-ق-ق",
      "prefixes": "—",
      "pattern": "فَعْل",
      "suffixes": "—",
      "meaning": "Wahrheit/Recht",
      "ref": "2:42",
      "verifyUrl": "https://corpus.quran.com/wordbyword.jsp?chapter=2&verse=42"
    },
    {
      "id": "dec_074",
      "word": "مَسْجِدٌ",
      "root": "س-ج-د",
      "prefixes": "مَـ",
      "pattern": "مَفْعِل (Ortsnomen)",
      "suffixes": "—",
      "meaning": "Niederwerfungsort",
      "ref": "2:114",
      "verifyUrl": "https://corpus.quran.com/wordbyword.jsp?chapter=2&verse=114"
    },
    {
      "id": "dec_075",
      "word": "مَغْفِرَةٌ",
      "root": "غ-ف-ر",
      "prefixes": "مَـ",
      "pattern": "مَفْعِلَة",
      "suffixes": "—",
      "meaning": "Vergebung",
      "ref": "2:268",
      "verifyUrl": "https://corpus.quran.com/wordbyword.jsp?chapter=2&verse=268"
    },
    {
      "id": "dec_076",
      "word": "تَفْسِيرٌ",
      "root": "ف-س-ر",
      "prefixes": "تَـ",
      "pattern": "تَفْعِيل (Masdar II)",
      "suffixes": "—",
      "meaning": "Erklärung/Deutung",
      "ref": "25:33",
      "verifyUrl": "https://corpus.quran.com/wordbyword.jsp?chapter=25&verse=33"
    },
    {
      "id": "dec_077",
      "word": "إِسْلَامٌ",
      "root": "س-ل-م",
      "prefixes": "إِـ",
      "pattern": "إِفْعَال (Masdar IV)",
      "suffixes": "—",
      "meaning": "Übergabe/Ergebung",
      "ref": "3:19",
      "verifyUrl": "https://corpus.quran.com/wordbyword.jsp?chapter=3&verse=19"
    },
    {
      "id": "dec_078",
      "word": "جِهَادٌ",
      "root": "ج-ه-د",
      "prefixes": "—",
      "pattern": "فِعَال (Masdar III)",
      "suffixes": "—",
      "meaning": "Anstrengung/Bemühung",
      "ref": "9:24",
      "verifyUrl": "https://corpus.quran.com/wordbyword.jsp?chapter=9&verse=24"
    },
    {
      "id": "dec_079",
      "word": "اِسْتِغْفَارٌ",
      "root": "غ-ف-ر",
      "prefixes": "اِسْتِـ",
      "pattern": "اِسْتِفْعَال (Masdar X)",
      "suffixes": "—",
      "meaning": "Bitte um Vergebung",
      "ref": "71:10",
      "verifyUrl": "https://corpus.quran.com/wordbyword.jsp?chapter=71&verse=10"
    },
    {
      "id": "dec_080",
      "word": "اِهْتِدَاءٌ",
      "root": "ه-د-ي",
      "prefixes": "اِـ + ـتِـ",
      "pattern": "اِفْتِعَال (Masdar VIII)",
      "suffixes": "—",
      "meaning": "Weg-Finden",
      "ref": "—",
      "verifyUrl": "https://corpus.quran.com/qurandictionary.jsp?q=hdy"
    },
    {
      "id": "dec_081",
      "word": "أَكْبَرُ",
      "root": "ك-ب-ر",
      "prefixes": "أَ",
      "pattern": "أَفْعَل (Elativ)",
      "suffixes": "—",
      "meaning": "größer/am größten",
      "ref": "29:45",
      "verifyUrl": "https://corpus.quran.com/wordbyword.jsp?chapter=29&verse=45"
    },
    {
      "id": "dec_082",
      "word": "أَحْسَنُ",
      "root": "ح-س-ن",
      "prefixes": "أَ",
      "pattern": "أَفْعَل (Elativ)",
      "suffixes": "—",
      "meaning": "besser/am besten",
      "ref": "12:3",
      "verifyUrl": "https://corpus.quran.com/wordbyword.jsp?chapter=12&verse=3"
    },
    {
      "id": "dec_083",
      "word": "أَعْلَمُ",
      "root": "ع-ل-م",
      "prefixes": "أَ",
      "pattern": "أَفْعَل (Elativ)",
      "suffixes": "—",
      "meaning": "wissender/am besten wissend",
      "ref": "2:140",
      "verifyUrl": "https://corpus.quran.com/wordbyword.jsp?chapter=2&verse=140"
    },
    {
      "id": "dec_084",
      "word": "أَقْرَبُ",
      "root": "ق-ر-ب",
      "prefixes": "أَ",
      "pattern": "أَفْعَل (Elativ)",
      "suffixes": "—",
      "meaning": "näher/am nächsten",
      "ref": "4:11",
      "verifyUrl": "https://corpus.quran.com/wordbyword.jsp?chapter=4&verse=11"
    },
    {
      "id": "dec_085",
      "word": "أَكْثَرُ",
      "root": "ك-ث-ر",
      "prefixes": "أَ",
      "pattern": "أَفْعَل (Elativ)",
      "suffixes": "—",
      "meaning": "mehr/am meisten",
      "ref": "12:21",
      "verifyUrl": "https://corpus.quran.com/wordbyword.jsp?chapter=12&verse=21"
    },
    {
      "id": "dec_086",
      "word": "الْكِتَابُ",
      "root": "ك-ت-ب",
      "prefixes": "الـ",
      "pattern": "فِعَال",
      "suffixes": "—",
      "meaning": "das Buch/die Schrift",
      "ref": "2:2",
      "verifyUrl": "https://corpus.quran.com/wordbyword.jsp?chapter=2&verse=2"
    },
    {
      "id": "dec_087",
      "word": "الرَّحْمَٰنِ",
      "root": "ر-ح-م",
      "prefixes": "الـ",
      "pattern": "فَعْلَان (Intensiv)",
      "suffixes": "—",
      "meaning": "der intensiv Barmherzige",
      "ref": "1:1",
      "verifyUrl": "https://corpus.quran.com/wordbyword.jsp?chapter=1&verse=1"
    },
    {
      "id": "dec_088",
      "word": "الصِّرَاطَ",
      "root": "ص-ر-ط",
      "prefixes": "الـ",
      "pattern": "فِعَال",
      "suffixes": "—",
      "meaning": "den Weg",
      "ref": "1:6",
      "verifyUrl": "https://corpus.quran.com/wordbyword.jsp?chapter=1&verse=6"
    },
    {
      "id": "dec_089",
      "word": "الْحَمْدُ",
      "root": "ح-م-د",
      "prefixes": "الـ",
      "pattern": "فَعْل (Masdar)",
      "suffixes": "—",
      "meaning": "das Lob",
      "ref": "1:2",
      "verifyUrl": "https://corpus.quran.com/wordbyword.jsp?chapter=1&verse=2"
    },
    {
      "id": "dec_090",
      "word": "الْعَالَمِينَ",
      "root": "ع-ل-م",
      "prefixes": "الـ",
      "pattern": "فَاعَل (Nomen)",
      "suffixes": "ينَ",
      "meaning": "die Welten/Geschöpfe",
      "ref": "1:2",
      "verifyUrl": "https://corpus.quran.com/wordbyword.jsp?chapter=1&verse=2"
    },
    {
      "id": "dec_091",
      "word": "بِسْمِ",
      "root": "س-م-و",
      "prefixes": "بِـ",
      "pattern": "اِسْم (فِعْل)",
      "suffixes": "—",
      "meaning": "im Namen",
      "ref": "1:1",
      "verifyUrl": "https://corpus.quran.com/wordbyword.jsp?chapter=1&verse=1"
    },
    {
      "id": "dec_092",
      "word": "لِلَّهِ",
      "root": "أ-ل-ه",
      "prefixes": "لِـ",
      "pattern": "Eigenname",
      "suffixes": "—",
      "meaning": "für Gott / Gott gehört",
      "ref": "1:2",
      "verifyUrl": "https://corpus.quran.com/wordbyword.jsp?chapter=1&verse=2"
    },
    {
      "id": "dec_093",
      "word": "فِيهِ",
      "root": "—",
      "prefixes": "فِي (Präp.)",
      "pattern": "—",
      "suffixes": "هِ (3ms)",
      "meaning": "in ihm/darin",
      "ref": "2:2",
      "verifyUrl": "https://corpus.quran.com/wordbyword.jsp?chapter=2&verse=2"
    },
    {
      "id": "dec_094",
      "word": "عَلَيْهِمْ",
      "root": "—",
      "prefixes": "عَلَى (Präp.)",
      "pattern": "—",
      "suffixes": "هِمْ (3mp)",
      "meaning": "auf ihnen",
      "ref": "1:7",
      "verifyUrl": "https://corpus.quran.com/wordbyword.jsp?chapter=1&verse=7"
    },
    {
      "id": "dec_095",
      "word": "مِنْهُمْ",
      "root": "—",
      "prefixes": "مِنْ (Präp.)",
      "pattern": "—",
      "suffixes": "هُمْ (3mp)",
      "meaning": "von ihnen",
      "ref": "2:75",
      "verifyUrl": "https://corpus.quran.com/wordbyword.jsp?chapter=2&verse=75"
    },
    {
      "id": "dec_096",
      "word": "رَبَّهُمْ",
      "root": "ر-ب-ب",
      "prefixes": "—",
      "pattern": "فَعّ",
      "suffixes": "هُمْ (3mp)",
      "meaning": "ihren Herrn",
      "ref": "2:5",
      "verifyUrl": "https://corpus.quran.com/wordbyword.jsp?chapter=2&verse=5"
    },
    {
      "id": "dec_097",
      "word": "أَنْفُسَهُمْ",
      "root": "ن-ف-س",
      "prefixes": "—",
      "pattern": "أَفْعُل (Plural)",
      "suffixes": "هُمْ (3mp)",
      "meaning": "ihre Selbste/sich selbst",
      "ref": "2:9",
      "verifyUrl": "https://corpus.quran.com/wordbyword.jsp?chapter=2&verse=9"
    },
    {
      "id": "dec_098",
      "word": "كِتَابَهُ",
      "root": "ك-ت-ب",
      "prefixes": "—",
      "pattern": "فِعَال",
      "suffixes": "هُ (3ms)",
      "meaning": "sein Buch",
      "ref": "69:19",
      "verifyUrl": "https://corpus.quran.com/wordbyword.jsp?chapter=69&verse=19"
    },
    {
      "id": "dec_099",
      "word": "أَيْدِيكُمْ",
      "root": "ي-د-ي",
      "prefixes": "—",
      "pattern": "أَفْعُل (Plural)",
      "suffixes": "كُمْ (2mp)",
      "meaning": "eure Hände",
      "ref": "5:11",
      "verifyUrl": "https://corpus.quran.com/wordbyword.jsp?chapter=5&verse=11"
    },
    {
      "id": "dec_100",
      "word": "رَسُولَهُ",
      "root": "ر-س-ل",
      "prefixes": "—",
      "pattern": "فَعُول",
      "suffixes": "هُ (3ms)",
      "meaning": "seinen Gesandten",
      "ref": "48:29",
      "verifyUrl": "https://corpus.quran.com/wordbyword.jsp?chapter=48&verse=29"
    },
    {
      "id": "dec_101",
      "word": "قَالَ",
      "root": "ق-و-ل",
      "prefixes": "—",
      "pattern": "فَعَلَ (I, hohl)",
      "suffixes": "—",
      "meaning": "er sagte",
      "ref": "2:30",
      "verifyUrl": "https://corpus.quran.com/wordbyword.jsp?chapter=2&verse=30"
    },
    {
      "id": "dec_102",
      "word": "كَانَ",
      "root": "ك-و-ن",
      "prefixes": "—",
      "pattern": "فَعَلَ (I, hohl)",
      "suffixes": "—",
      "meaning": "er war",
      "ref": "2:34",
      "verifyUrl": "https://corpus.quran.com/wordbyword.jsp?chapter=2&verse=34"
    },
    {
      "id": "dec_103",
      "word": "هَدَى",
      "root": "ه-د-ي",
      "prefixes": "—",
      "pattern": "فَعَلَ (I, defektiv)",
      "suffixes": "—",
      "meaning": "er leitete recht",
      "ref": "2:213",
      "verifyUrl": "https://corpus.quran.com/wordbyword.jsp?chapter=2&verse=213"
    },
    {
      "id": "dec_104",
      "word": "دَعَا",
      "root": "د-ع-و",
      "prefixes": "—",
      "pattern": "فَعَلَ (I, defektiv)",
      "suffixes": "—",
      "meaning": "er rief",
      "ref": "2:186",
      "verifyUrl": "https://corpus.quran.com/wordbyword.jsp?chapter=2&verse=186"
    },
    {
      "id": "dec_105",
      "word": "جَاءَ",
      "root": "ج-ي-أ",
      "prefixes": "—",
      "pattern": "فَعَلَ (I, hohl (Mittel-Ya) + hamziert (Endradikal))",
      "suffixes": "—",
      "meaning": "er kam",
      "ref": "2:87",
      "verifyUrl": "https://corpus.quran.com/wordbyword.jsp?chapter=2&verse=87"
    },
    {
      "id": "dec_106",
      "word": "عَلِيمٌ",
      "root": "ع-ل-م",
      "prefixes": "—",
      "pattern": "فَعِيل (Intensiv)",
      "suffixes": "—",
      "meaning": "viel-wissend (Intensivform)",
      "ref": "2:32",
      "verifyUrl": "https://corpus.quran.com/wordbyword.jsp?chapter=2&verse=32"
    },
    {
      "id": "dec_107",
      "word": "رَحِيمٌ",
      "root": "ر-ح-م",
      "prefixes": "—",
      "pattern": "فَعِيل (dauerhafte Eigenschaft)",
      "suffixes": "—",
      "meaning": "Barmherzig",
      "ref": "1:1",
      "verifyUrl": "https://corpus.quran.com/wordbyword.jsp?chapter=1&verse=1"
    },
    {
      "id": "dec_108",
      "word": "سَمِيعٌ",
      "root": "س-م-ع",
      "prefixes": "—",
      "pattern": "فَعِيل",
      "suffixes": "—",
      "meaning": "viel-hörend (Intensivform)",
      "ref": "2:127",
      "verifyUrl": "https://corpus.quran.com/wordbyword.jsp?chapter=2&verse=127"
    },
    {
      "id": "dec_109",
      "word": "بَصِيرٌ",
      "root": "ب-ص-ر",
      "prefixes": "—",
      "pattern": "فَعِيل",
      "suffixes": "—",
      "meaning": "viel-sehend (Intensivform)",
      "ref": "2:96",
      "verifyUrl": "https://corpus.quran.com/wordbyword.jsp?chapter=2&verse=96"
    },
    {
      "id": "dec_110",
      "word": "قَدِيرٌ",
      "root": "ق-د-ر",
      "prefixes": "—",
      "pattern": "فَعِيل",
      "suffixes": "—",
      "meaning": "äußerst fähig (Intensivform)",
      "ref": "2:20",
      "verifyUrl": "https://corpus.quran.com/wordbyword.jsp?chapter=2&verse=20"
    },
    {
      "id": "dec_111",
      "word": "غَفُورٌ",
      "root": "غ-ف-ر",
      "prefixes": "—",
      "pattern": "فَعُول",
      "suffixes": "—",
      "meaning": "viel-vergebend (Intensivform)",
      "ref": "2:173",
      "verifyUrl": "https://corpus.quran.com/wordbyword.jsp?chapter=2&verse=173"
    },
    {
      "id": "dec_112",
      "word": "كَفَّارٌ",
      "root": "ك-ف-ر",
      "prefixes": "—",
      "pattern": "فَعَّال (Intensiv)",
      "suffixes": "—",
      "meaning": "stark Verdeckender",
      "ref": "2:276",
      "verifyUrl": "https://corpus.quran.com/wordbyword.jsp?chapter=2&verse=276"
    },
    {
      "id": "dec_113",
      "word": "جَبَّارٌ",
      "root": "ج-ب-ر",
      "prefixes": "—",
      "pattern": "فَعَّال (Intensiv)",
      "suffixes": "—",
      "meaning": "Allbezwingender",
      "ref": "59:23",
      "verifyUrl": "https://corpus.quran.com/wordbyword.jsp?chapter=59&verse=23"
    },
    {
      "id": "dec_114",
      "word": "صَمَدٌ",
      "root": "ص-م-د",
      "prefixes": "—",
      "pattern": "فَعَل",
      "suffixes": "—",
      "meaning": "der Beständige",
      "ref": "112:2",
      "verifyUrl": "https://corpus.quran.com/wordbyword.jsp?chapter=112&verse=2"
    },
    {
      "id": "dec_115",
      "word": "أَنْعَمْتَ",
      "root": "ن-ع-م",
      "prefixes": "أَ (IV)",
      "pattern": "أَفْعَلَ (IV)",
      "suffixes": "تَ (2ms)",
      "meaning": "du hast begünstigt",
      "ref": "1:7",
      "verifyUrl": "https://corpus.quran.com/wordbyword.jsp?chapter=1&verse=7"
    },
    {
      "id": "dec_116",
      "word": "أَقِيمُوا",
      "root": "ق-و-م",
      "prefixes": "أَ (IV)",
      "pattern": "أَفْعَلَ (IV) Imperativ",
      "suffixes": "وا (2mp)",
      "meaning": "verrichtet!",
      "ref": "2:43",
      "verifyUrl": "https://corpus.quran.com/wordbyword.jsp?chapter=2&verse=43"
    },
    {
      "id": "dec_117",
      "word": "أَرْسَلْنَا",
      "root": "ر-س-ل",
      "prefixes": "أَ (IV)",
      "pattern": "أَفْعَلَ (IV)",
      "suffixes": "نَا (1p)",
      "meaning": "wir sandten",
      "ref": "2:151",
      "verifyUrl": "https://corpus.quran.com/wordbyword.jsp?chapter=2&verse=151"
    }
  ]
}